{"metadata":{"date":"2022-02-17T10:22:48.992554646-06:00","gnfinderVersion":"v0.17.0-2-g401ad6e","inputFile":"STDIN","nameFindingSec":0.002570425,"nameVerifSec":0.06788069,"totalSec":0.07045112,"withBayes":true,"withOddsAdjustment":false,"withPositionInBytes":false,"withVerification":true,"wordsAround":2,"language":"eng","withLanguageDetection":false,"totalWords":3051,"totalNameCandidates":352,"totalNames":1},"names":[{"cardinality":2,"verbatim":"Saccharomyces cerevisiae","name":"Saccharomyces cerevisiae","oddsLog10":11.307744472389626,"start":2053,"end":2077,"annotationNomenType":"NO_ANNOT","wordsBefore":["budding","yeast"],"wordsAfter":["for","direct"],"verification":{"id":"148aa17a-2eac-5ca7-bac0-e87a031c71a5","name":"Saccharomyces cerevisiae","matchType":"Exact","bestResult":{"dataSourceId":1,"dataSourceTitleShort":"Catalogue of Life","curation":"Curated","recordId":"4TWCR","outlink":"https://www.catalogueoflife.org/data/taxon/4TWCR","entryDate":"2021-11-20","matchedName":"Saccharomyces cerevisiae (Desm.) Meyen","matchedCardinality":2,"matchedCanonicalSimple":"Saccharomyces cerevisiae","matchedCanonicalFull":"Saccharomyces cerevisiae","currentRecordId":"4TWCR","currentName":"Saccharomyces cerevisiae (Desm.) Meyen","currentCardinality":2,"currentCanonicalSimple":"Saccharomyces cerevisiae","currentCanonicalFull":"Saccharomyces cerevisiae","isSynonym":false,"classificationPath":"Biota|Fungi|Ascomycota|Saccharomycetes|Saccharomycetales|Saccharomycetaceae|Saccharomyces|Saccharomyces cerevisiae","classificationRanks":"unranked|kingdom|phylum|class|order|family|genus|species","classificationIds":"5T6MX|F|SM|HN|3ZK|FVC|7BFM|4TWCR","editDistance":0,"stemEditDistance":0,"matchType":"Exact","scoreDetails":{"infraSpecificRankScore":0,"fuzzyLessScore":1,"curatedDataScore":1,"authorMatchScore":0.2857143,"acceptedNameScore":1,"parsingQualityScore":1}},"dataSourcesNum":21,"curation":"Curated"}}]}
